setup.cfg
setup.py
htmloutputparallel/__init__.py
htmloutputparallel/htmloutputparallel.py
htmloutputparallel/nose_wrapper.py
htmloutputparallel/version.py
htmloutputparallel/templates/report-outlook-friendly.jinja2
htmloutputparallel/templates/report.jinja2
nose_html_output_parallel.egg-info/PKG-INFO
nose_html_output_parallel.egg-info/SOURCES.txt
nose_html_output_parallel.egg-info/dependency_links.txt
nose_html_output_parallel.egg-info/entry_points.txt
nose_html_output_parallel.egg-info/requires.txt
nose_html_output_parallel.egg-info/top_level.txt